aluctr/alu.v
module ALU (
    input  [31:0] A,       
    input  [31:0] B,       
    input  [4:0]  ALUop,   
    output reg [31:0] Y,   
    output zero            
);

    always @(*) begin
        case (ALUop)
        // R-type
            5'b00000: Y = A + B;                   // ADD
            5'b00001: Y = A - B;                   // SUB
            5'b00010: Y = A << B[4:0];             // SLL
            5'b00011: Y = ($signed(A) < $signed(B)) ? 32'd1 : 32'd0;  // SLT
            5'b00100: Y = (A < B) ? 32'd1 : 32'd0;  // SLTU
            5'b00101: Y = A ^ B;                   // XOR
            5'b00110: Y = A >> B[4:0];             // SRL
            5'b00111: Y = $signed(A) >>> B[4:0];   // SRA
            5'b01000: Y = A | B;                   // OR
            5'b01001: Y = A & B;                   // AND

        // B-type
            5'b01010: Y = (A == B) ? 32'd1 : 32'd0; // BEQ
            5'b01011: Y = (A != B) ? 32'd1 : 32'd0; // BNE
            5'b01100: Y = ($signed(A) < $signed(B)) ? 32'd1 : 32'd0;  // BLT
            5'b01101: Y = ($signed(A) >= $signed(B)) ? 32'd1 : 32'd0; // BGE
            5'b01110: Y = (A < B) ? 32'd1 : 32'd0;   // BLTU
            5'b01111: Y = (A >= B) ? 32'd1 : 32'd0;  // BGEU

        default:  Y = 32'd0; // 沒定義到的就給 0
        endcase
    end

    assign zero = (Y == 32'd0);

endmodule

ALUctr_alu_imm_F/aluctr.v
/*
******************************************************************************
* RISC-V RV32I Instruction Set (ALU 相關指令) 簡要表格
* ----------------------------------------------------------------------------
* 以下列出部分和 ALU 有關之指令 (R 類型與 I 類型)，實際上 RV32I 還包含
* load/store、branch、jump、system 等其他指令，請自行參閱官方文件。
*
* R-type (opcode = 0110011):
* ----------------------------------------------------------------------------
* 指令   | funct7   | funct3  | opcode   | 功能說明
* ----------------------------------------------------------------------------
* ADD    | 0000000  | 000     | 0110011  | Rd = Rs1 + Rs2
* SUB    | 0100000  | 000     | 0110011  | Rd = Rs1 - Rs2
* SLL    | 0000000  | 001     | 0110011  | Rd = Rs1 << (Rs2[4:0])
* SLT    | 0000000  | 010     | 0110011  | Rd = (Rs1 < Rs2) ? 1 : 0 (有號比較)
* SLTU   | 0000000  | 011     | 0110011  | Rd = (Rs1 < Rs2) ? 1 : 0 (無號比較)
* XOR    | 0000000  | 100     | 0110011  | Rd = Rs1 ^ Rs2
* SRL    | 0000000  | 101     | 0110011  | Rd = Rs1 >> (Rs2[4:0]) (邏輯右移)
* SRA    | 0100000  | 101     | 0110011  | Rd = Rs1 >> (Rs2[4:0]) (算術右移)
* OR     | 0000000  | 110     | 0110011  | Rd = Rs1 | Rs2
* AND    | 0000000  | 111     | 0110011  | Rd = Rs1 & Rs2
*
* I-type (opcode = 0010011)：
* ----------------------------------------------------------------------------
* 指令    | funct7(部分用於移位) | funct3  | opcode   | 功能說明
* ----------------------------------------------------------------------------
* ADDI    |    -    | 000     | 0010011  | Rd = Rs1 + sign_ext(imm)
* SLTI    |    -    | 010     | 0010011  | Rd = (Rs1 < imm) ? 1 : 0
* SLTIU   |    -    | 011     | 0010011  | Rd = (Rs1 < imm) ? 1 : 0 (無號)
* XORI    |    -    | 100     | 0010011  | Rd = Rs1 ^ imm
* ORI     |    -    | 110     | 0010011  | Rd = Rs1 | imm
* ANDI    |    -    | 111     | 0010011  | Rd = Rs1 & imm
* SLLI    | 0000000 | 001     | 0010011  | Rd = Rs1 << shamt
* SRLI    | 0000000 | 101     | 0010011  | Rd = Rs1 >> shamt (邏輯)
* SRAI    | 0100000 | 101     | 0010011  | Rd = Rs1 >> shamt (算術)
*
******************************************************************************
*/

//------------------------- ALU Control 模組 -------------------------
module ALUctr (
    input  [6:0] opcode,      // 指令的 opcode (例如 0110011, 0010011 等)
    input  [2:0] funct3,      // 指令的 funct3 欄位
    input  [6:0] funct7,      // 指令的 funct7 欄位 (只需部分 bit 區分 ADD/SUB, SRL/SRA)
    output reg [4:0] ALUop     // ALU 操作碼 (可依實際需求擴增位數)
);

    // 定義 ALUop 常數 (依據自己的設計需求而定)
    localparam ALU_ADD  = 5'b00000;
    localparam ALU_SUB  = 5'b00001;
    localparam ALU_SLL  = 5'b00010;
    localparam ALU_SLT  = 5'b00011;
    localparam ALU_SLTU = 5'b00100;
    localparam ALU_XOR  = 5'b00101;
    localparam ALU_SRL  = 5'b00110;
    localparam ALU_SRA  = 5'b00111;
    localparam ALU_OR   = 5'b01000;
    localparam ALU_AND  = 5'b01001;
    // 如果要支援立即數或其他運算，可再擴增
      // B-type 指令
    localparam ALU_BEQ  = 5'b01010;
    localparam ALU_BNE  = 5'b01011;
    localparam ALU_BLT  = 5'b01100;
    localparam ALU_BGE  = 5'b01101;
    localparam ALU_BLTU = 5'b01110;
    localparam ALU_BGEU = 5'b01111;

    always @(*) begin
        case (opcode)
            7'b0110011: // R-type
                begin
                    case (funct3)
                    
    //ref : https://velog.io/@taegon1998/2.2-2-Basic-of-RISC-V
                        3'b000: // ADD / SUB
                            ALUop = (funct7[5] == 1'b1) ? ALU_SUB : ALU_ADD;
                        3'b001: ALUop = ALU_SLL; //SLL
                        3'b010: ALUop = ALU_SLT; //SLT
                        3'b011: ALUop = ALU_SLTU; //SLTU
                        3'b100: ALUop = ALU_XOR; //XOR
                        //---------------same funct3-------------------------
                        3'b101: // SRL / SRA
                            ALUop = (funct7[5] == 1'b1) ? ALU_SRA : ALU_SRL;
                        //---------------------------------------------------
                        3'b110: ALUop = ALU_OR;
                        3'b111: ALUop = ALU_AND;
                        default: ALUop = ALU_ADD;  // 預設給個安全值
                    endcase
                end
            7'b0010011: // I-type (ADDI, SLTI, XORI, ORI, ANDI, SLLI, SRLI, SRAI ...)
                begin
    //ref : https://www.chegg.com/homework-help/questions-and-answers/risc-v-instruction-show-value-opcode-op-source-register-rsl-destination-register-id-fields-q85052084
                    case (funct3)
                        3'b000: ALUop = ALU_ADD;   // ADDI
                        3'b010: ALUop = ALU_SLT;   // SLTI
                        3'b011: ALUop = ALU_SLTU;  // SLTIU
                        3'b100: ALUop = ALU_XOR;   // XORI
                        3'b110: ALUop = ALU_OR;    // ORI
                        3'b111: ALUop = ALU_AND;   // ANDI
                        3'b001: ALUop = ALU_SLL;   // SLLI
                        3'b101: // SRLI / SRAI
                            ALUop = (funct7[5] == 1'b1) ? ALU_SRA : ALU_SRL;
                        default: ALUop = ALU_ADD; 
                    endcase
                end
            7'b1100011: // B-type (Branch)
                case (funct3)
                    3'b000: ALUop = ALU_BEQ;
                    3'b001: ALUop = ALU_BNE;
                    3'b100: ALUop = ALU_BLT;
                    3'b101: ALUop = ALU_BGE;
                    3'b110: ALUop = ALU_BLTU;
                    3'b111: ALUop = ALU_BGEU;
                    default: ALUop = ALU_ADD;
                endcase
            default:
                ALUop = ALU_ADD; // 其他暫時預設成 ADD
        endcase
    end

endmodule

aluctr/tb.v
`timescale 1ns / 100ps
/*
          ┌──────────────────────────────────────────────────┐
          │                     ALUctr                      │
          ├──────────────────────────────────────────────────┤
          │ opcode [6:0]  ─────────► │                      │
          │ funct3 [2:0]  ─────────► │                      │
          │ funct7 [6:0]  ─────────► │   ALU 操作碼產生     │
          │                          │                      │
          │       ALUop [4:0]  ◄─────│                      │
          └──────────────────────────────────────────────────┘
                               │
                               ▼
          ┌──────────────────────────────────────────────────┐
          │                     ALU                         │
          ├──────────────────────────────────────────────────┤
          │ A [31:0]    ─────────────────────────────────►   │
          │ B [31:0]    ─────────────────────────────────►   │
          │ ALUop [4:0] ────────────────────────────────►   │
          │                                                 │
          │      (ALU 運算: ADD, SUB, SLL, SLT, AND, OR...)  │
          │                                                 │
          │    Y [31:0]   ◄───────────────────────────────  │
          │    zero       ◄───────────────────────────────  │
          └──────────────────────────────────────────────────┘
*/
module ALU_ALUctr_tb;
    reg [31:0] A, B;
    reg [6:0] opcode;
    reg [2:0] funct3;
    reg [6:0] funct7;
    wire [4:0] ALUop;
    wire [31:0] Y;
    wire zero;

    // ALU 控制單元 (ALUctr) 實例化
    ALUctr alu_ctrl (
        .opcode(opcode),
        .funct3(funct3),
        .funct7(funct7),
        .ALUop(ALUop)
    );

    // ALU 實例化
    ALU alu (
        .A(A),
        .B(B),
        .ALUop(ALUop),
        .Y(Y),
        .zero(zero)
    );

    // 測試程序
    initial begin
        $display("ALU+aluctr : Testbench");
        $dumpfile("ALU_ALUctr_tb.vcd");  // VCD 波形輸出
        $dumpvars(0, ALU_ALUctr_tb);
        
        $display("------------------R-type 指令-------------------");
        // 測試 R-type 指令
        opcode = 7'b0110011; // R-type 指令

        // 測試 ADD (0000000 funct7, 000 funct3)
        A = 32'h00000010; B = 32'h00000020; funct3 = 3'b000; funct7 = 7'b0000000;
        #10;
        $display("ALUop : %b", ALUop);
        $display("ADD: A=%h, B=%h, Y=%h (Expect 30)", A, B, Y);

        // 測試 SUB (0100000 funct7, 000 funct3)
        A = 32'h00000030; B = 32'h00000010; funct3 = 3'b000; funct7 = 7'b0100000;
        #10;
        $display("SUB: A=%h, B=%h, Y=%h (Expect 20)", A, B, Y);

        // 測試 SLL (0000000 funct7, 001 funct3)
        A = 32'h00000001; B = 32'h00000002; funct3 = 3'b001; funct7 = 7'b0000000;
        #10;
        $display("SLL: A=%h, B=%h, Y=%h (Expect 4)", A, B, Y);

        // 測試 SLT (0000000 funct7, 010 funct3) (有號比較)
        A = 32'hFFFFFFF0; B = 32'h00000010; funct3 = 3'b010; funct7 = 7'b0000000;
        #10;
        $display("SLT: A=%h, B=%h, Y=%h (Expect 1)", A, B, Y);

        // 測試 SLTU (0000000 funct7, 011 funct3) (無號比較)
        A = 32'h00000010; B = 32'hFFFFFFF0; funct3 = 3'b011; funct7 = 7'b0000000;
        #10;
        $display("SLTU: A=%h, B=%h, Y=%h (Expect 1)", A, B, Y);

        // 測試 XOR (0000000 funct7, 100 funct3)
        A = 32'h0000000F; B = 32'h000000F0; funct3 = 3'b100; funct7 = 7'b0000000;
        #10;
        $display("XOR: A=%h, B=%h, Y=%h (Expect 0xFF)", A, B, Y);

        // 測試 SRL (0000000 funct7, 101 funct3)
        // 00000010 >> 2 = 00000004
        A = 32'h00000010; B = 32'h00000002; funct3 = 3'b101; funct7 = 7'b0000000;
        #10;
        $display("SRL: A=%h, B=%h, Y=%h (Expect 4)", A, B, Y);

        // 測試 SRA (0100000 funct7, 101 funct3)
        // 80000000 >> 2 = E0000000
        A = 32'h80000000; B = 32'h00000002; funct3 = 3'b101; funct7 = 7'b0100000;
        #10;
        $display("SRA: A=%h, B=%h, Y=%h (Expect E0000000)", A, B, Y);

        // 測試 OR (0000000 funct7, 110 funct3)
        // 0000F0F0 | 00F000F0 = 00F0F0F0
        A = 32'h0000F0F0; B = 32'h00F000F0; funct3 = 3'b110; funct7 = 7'b0000000;
        #10;
        $display("OR: A=%h, B=%h, Y=%h (Expect 00F0F0F0)", A, B, Y);

        // 測試 AND (0000000 funct7, 111 funct3)
        A = 32'h0000F0F0; B = 32'h00F000F0; funct3 = 3'b111; funct7 = 7'b0000000;
        #10;
        $display("AND: A=%h, B=%h, Y=%h (Expect 00F000F0)", A, B, Y);

        $display("------------------I-type 指令-------------------");
        // 測試 I-type 指令 基本差別在有沒有牽扯到imm
        opcode = 7'b0010011; // I-type 指令
        $display("ALUop : %b", ALUop);
        // 測試 ADDI (000 funct3)
        A = 32'h00000010; B = 32'h00000010; funct3 = 3'b000; funct7 = 7'b0000000;
        #10;
        $display("ADDI: A=%h, B=%h, Y=%h (Expect 20)", A, B, Y);
        //SLTI rd, rs1, imm  // rd = (rs1 < imm) ? 1 : 0 （有符號比較）
        // 測試 SLTI (010 funct3)
        //SLTI x5, x1, 
        //比較 -5 < 3（成立），因此 x5 = 1。
        A = 32'hFFFFFFF0; B = 32'h00000010; funct3 = 3'b010; funct7 = 7'b0000000;
        #10;
        $display("SLTI: A=%h, B=%h, Y=%h (Expect 1)", A, B, Y);
        //無符號比較
        // LTI x5, x1, 
        // 比較 |-5| < 3（不盛成立），因此 x5 = 0
        // 測試 SLTIU (011 funct3)
        A = 32'h00000010; B = 32'hFFFFFFF0; funct3 = 3'b011; funct7 = 7'b0000000;
        #10;
        $display("SLTIU: A=%h, B=%h, Y=%h (Expect 1)", A, B, Y);

        // 測試 XORI (100 funct3)
        // 與常數immXOR
        A = 32'h0000000F; B = 32'h000000F0; funct3 = 3'b100; funct7 = 7'b0000000;
        #10;
        $display("XORI: A=%h, B=%h, Y=%h (Expect FFF)", A, B, Y);

        // 測試 ORI (110 funct3)
        
        A = 32'h0000F0F0; B = 32'h00F000F0; funct3 = 3'b110; funct7 = 7'b0000000;
        #10;
        $display("ORI: A=%h, B=%h, Y=%h (Expect F0F0F0F0)", A, B, Y);

        // 測試 ANDI (111 funct3)
        A = 32'h0000F0F0; B = 32'h00F000F0; funct3 = 3'b111; funct7 = 7'b0000000;
        #10;
        $display("ANDI: A=%h, B=%h, Y=%h (Expect 00F000F0)", A, B, Y);

        // 測試 zero flag
        A = 32'h00000010; B = 32'h00000010; funct3 = 3'b000; funct7 = 7'b0100000;
        #10;
        $display("Zero Flag: A=%h, B=%h, Y=%h, Zero=%b (Expect Zero=1)", A, B, Y, zero);
        #10
        
        $display("------------------B-type 指令-------------------");
        opcode = 7'b1100011; // B-type 指令
        $display("op : %b", opcode);
        // 測試 BEQ (A == B)
        A = 32'h00000010; B = 32'h00000010; funct3 = 3'b000;
        #10;
        $display("ALUop : %b", ALUop);
        $display("BEQ: A=%h, B=%h, Y=%b (Expect 1)", A, B, Y);

        // 測試 BNE (A != B)
        A = 32'h00000010; B = 32'h00000020; funct3 = 3'b001;
        #10;
        $display("BNE: A=%h, B=%h, Y=%h (Expect 1)", A, B, Y);

        // 測試 BLT (A < B, 有號)
        A = 32'hFFFFFFF0; B = 32'h00000010; funct3 = 3'b100;
        #10;
        $display("BLT: A=%h, B=%h, Y=%h (Expect 1)", A, B, Y);

        // 測試 BGE (A >= B, 有號)
        A = 32'h00000010; B = 32'hFFFFFFF0; funct3 = 3'b101;
        #10;
        $display("BGE: A=%h, B=%h, Y=%h (Expect 1)", A, B, Y);

        // 測試 BLTU (A < B, 無號)
        A = 32'h00000010; B = 32'hFFFFFFF0; funct3 = 3'b110;
        #10;
        $display("BLTU: A=%h, B=%h, Y=%h (Expect 1)", A, B, Y);

        // 測試 BGEU (A >= B, 無號)
        A = 32'hFFFFFFF0; B = 32'h00000010; funct3 = 3'b111;
        #10;
        $display("BGEU: A=%h, B=%h, Y=%h (Expect 1)", A, B, Y);


        $finish;
    end
endmodule

ALUctr_alu_imm_F/ALU_ALUctr_tb.vcd
$date
	Mon Mar 10 17:43:33 2025
$end
$version
	Icarus Verilog
$end
$timescale
	100ps
$end
$scope module ALU_ALUctr_tb $end
$var wire 1 ! zero $end
$var wire 32 " Y [31:0] $end
$var wire 5 # ALUop [4:0] $end
$var reg 32 $ A [31:0] $end
$var reg 32 % B [31:0] $end
$var reg 3 & funct3 [2:0] $end
$var reg 7 ' funct7 [6:0] $end
$var reg 7 ( opcode [6:0] $end
$scope module alu $end
$var wire 32 ) A [31:0] $end
$var wire 32 * B [31:0] $end
$var wire 1 ! zero $end
$var wire 5 + ALUop [4:0] $end
$var reg 32 , Y [31:0] $end
$upscope $end
$scope module alu_ctrl $end
$var wire 3 - funct3 [2:0] $end
$var wire 7 . funct7 [6:0] $end
$var wire 7 / opcode [6:0] $end
$var reg 5 0 ALUop [4:0] $end
$upscope $end
$upscope $end
$enddefinitions $end
#0
$dumpvars
b0 0
b110011 /
b0 .
b0 -
b110000 ,
b0 +
b100000 *
b10000 )
b110011 (
b0 '
b0 &
b100000 %
b10000 $
b0 #
b110000 "
0!
$end
#100
b1 #
b1 +
b1 0
b100000 "
b100000 ,
b100000 '
b100000 .
b10000 %
b10000 *
b110000 $
b110000 )
#200
b10 #
b10 +
b10 0
b100 "
b100 ,
b0 '
b0 .
b1 &
b1 -
b10 %
b10 *
b1 $
b1 )
#300
b11 #
b11 +
b11 0
b1 "
b1 ,
b10 &
b10 -
b10000 %
b10000 *
b11111111111111111111111111110000 $
b11111111111111111111111111110000 )
#400
b100 #
b100 +
b100 0
0!
b1 "
b1 ,
b11 &
b11 -
b11111111111111111111111111110000 %
b11111111111111111111111111110000 *
b10000 $
b10000 )
#500
b11111111 "
b11111111 ,
b101 #
b101 +
b101 0
b100 &
b100 -
b11110000 %
b11110000 *
b1111 $
b1111 )
#600
b110 #
b110 +
b110 0
b100 "
b100 ,
b101 &
b101 -
b10 %
b10 *
b10000 $
b10000 )
#700
b111 #
b111 +
b111 0
b11100000000000000000000000000000 "
b11100000000000000000000000000000 ,
b100000 '
b100000 .
b10000000000000000000000000000000 $
b10000000000000000000000000000000 )
#800
b1000 #
b1000 +
b1000 0
0!
b111100001111000011110000 "
b111100001111000011110000 ,
b0 '
b0 .
b110 &
b110 -
b111100000000000011110000 %
b111100000000000011110000 *
b1111000011110000 $
b1111000011110000 )
#900
b11110000 "
b11110000 ,
b1001 #
b1001 +
b1001 0
b111 &
b111 -
#1000
b100000 "
b100000 ,
b0 #
b0 +
b0 0
b0 &
b0 -
b10000 %
b10000 *
b10000 $
b10000 )
b10011 (
b10011 /
#1100
b11 #
b11 +
b11 0
0!
b1 "
b1 ,
b10 &
b10 -
b11111111111111111111111111110000 $
b11111111111111111111111111110000 )
#1200
b100 #
b100 +
b100 0
0!
b1 "
b1 ,
b11 &
b11 -
b11111111111111111111111111110000 %
b11111111111111111111111111110000 *
b10000 $
b10000 )
#1300
b11111111 "
b11111111 ,
b101 #
b101 +
b101 0
b100 &
b100 -
b11110000 %
b11110000 *
b1111 $
b1111 )
#1400
b1000 #
b1000 +
b1000 0
b111100001111000011110000 "
b111100001111000011110000 ,
b110 &
b110 -
b111100000000000011110000 %
b111100000000000011110000 *
b1111000011110000 $
b1111000011110000 )
#1500
b11110000 "
b11110000 ,
b1001 #
b1001 +
b1001 0
b111 &
b111 -
#1600
b0 #
b0 +
b0 0
b100000 "
b100000 ,
b100000 '
b100000 .
b0 &
b0 -
b10000 %
b10000 *
b10000 $
b10000 )
#1800
b1 "
b1 ,
b1010 #
b1010 +
b1010 0
b1100011 (
b1100011 /
#1900
b1011 #
b1011 +
b1011 0
0!
b1 "
b1 ,
b1 &
b1 -
b100000 %
b100000 *
#2000
b1100 #
b1100 +
b1100 0
b100 &
b100 -
b10000 %
b10000 *
b11111111111111111111111111110000 $
b11111111111111111111111111110000 )
#2100
b1101 #
b1101 +
b1101 0
0!
b1 "
b1 ,
b101 &
b101 -
b11111111111111111111111111110000 %
b11111111111111111111111111110000 *
b10000 $
b10000 )
#2200
b1110 #
b1110 +
b1110 0
b110 &
b110 -
#2300
b1111 #
b1111 +
b1111 0
0!
b1 "
b1 ,
b111 &
b111 -
b10000 %
b10000 *
b11111111111111111111111111110000 $
b11111111111111111111111111110000 )
