aluctr/alu.v
module ALU (
    input  [31:0] A,       
    input  [31:0] B,       
    input  [4:0]  ALUop,   
    output reg [31:0] Y,   
    output zero            
);

    always @(*) begin
        case (ALUop)
        // R-type
            5'b00000: Y = A + B;                   // ADD
            5'b00001: Y = A - B;                   // SUB
            5'b00010: Y = A << B[4:0];             // SLL
            5'b00011: Y = ($signed(A) < $signed(B)) ? 32'd1 : 32'd0;  // SLT
            5'b00100: Y = (A < B) ? 32'd1 : 32'd0;  // SLTU
            5'b00101: Y = A ^ B;                   // XOR
            5'b00110: Y = A >> B[4:0];             // SRL
            5'b00111: Y = $signed(A) >>> B[4:0];   // SRA
            5'b01000: Y = A | B;                   // OR
            5'b01001: Y = A & B;                   // AND

        // B-type
            5'b01010: Y = (A == B) ? 32'd1 : 32'd0; // BEQ
            5'b01011: Y = (A != B) ? 32'd1 : 32'd0; // BNE
            5'b01100: Y = ($signed(A) < $signed(B)) ? 32'd1 : 32'd0;  // BLT
            5'b01101: Y = ($signed(A) >= $signed(B)) ? 32'd1 : 32'd0; // BGE
            5'b01110: Y = (A < B) ? 32'd1 : 32'd0;   // BLTU
            5'b01111: Y = (A >= B) ? 32'd1 : 32'd0;  // BGEU

        default:  Y = 32'd0; // 沒定義到的就給 0
        endcase
    end

    assign zero = (Y == 32'd0);

endmodule

ALUctr_alu_imm_F/aluctr.v
/*
******************************************************************************
* RISC-V RV32I Instruction Set (ALU 相關指令) 簡要表格
* ----------------------------------------------------------------------------
* 以下列出部分和 ALU 有關之指令 (R 類型與 I 類型)，實際上 RV32I 還包含
* load/store、branch、jump、system 等其他指令，請自行參閱官方文件。
*
* R-type (opcode = 0110011):
* ----------------------------------------------------------------------------
* 指令   | funct7   | funct3  | opcode   | 功能說明
* ----------------------------------------------------------------------------
* ADD    | 0000000  | 000     | 0110011  | Rd = Rs1 + Rs2
* SUB    | 0100000  | 000     | 0110011  | Rd = Rs1 - Rs2
* SLL    | 0000000  | 001     | 0110011  | Rd = Rs1 << (Rs2[4:0])
* SLT    | 0000000  | 010     | 0110011  | Rd = (Rs1 < Rs2) ? 1 : 0 (有號比較)
* SLTU   | 0000000  | 011     | 0110011  | Rd = (Rs1 < Rs2) ? 1 : 0 (無號比較)
* XOR    | 0000000  | 100     | 0110011  | Rd = Rs1 ^ Rs2
* SRL    | 0000000  | 101     | 0110011  | Rd = Rs1 >> (Rs2[4:0]) (邏輯右移)
* SRA    | 0100000  | 101     | 0110011  | Rd = Rs1 >> (Rs2[4:0]) (算術右移)
* OR     | 0000000  | 110     | 0110011  | Rd = Rs1 | Rs2
* AND    | 0000000  | 111     | 0110011  | Rd = Rs1 & Rs2
*
* I-type (opcode = 0010011)：
* ----------------------------------------------------------------------------
* 指令    | funct7(部分用於移位) | funct3  | opcode   | 功能說明
* ----------------------------------------------------------------------------
* ADDI    |    -    | 000     | 0010011  | Rd = Rs1 + sign_ext(imm)
* SLTI    |    -    | 010     | 0010011  | Rd = (Rs1 < imm) ? 1 : 0
* SLTIU   |    -    | 011     | 0010011  | Rd = (Rs1 < imm) ? 1 : 0 (無號)
* XORI    |    -    | 100     | 0010011  | Rd = Rs1 ^ imm
* ORI     |    -    | 110     | 0010011  | Rd = Rs1 | imm
* ANDI    |    -    | 111     | 0010011  | Rd = Rs1 & imm
* SLLI    | 0000000 | 001     | 0010011  | Rd = Rs1 << shamt
* SRLI    | 0000000 | 101     | 0010011  | Rd = Rs1 >> shamt (邏輯)
* SRAI    | 0100000 | 101     | 0010011  | Rd = Rs1 >> shamt (算術)
*
******************************************************************************
*/

//------------------------- ALU Control 模組 -------------------------
module ALUctr (
    input  [6:0] opcode,      // 指令的 opcode (例如 0110011, 0010011 等)
    input  [2:0] funct3,      // 指令的 funct3 欄位
    input  [6:0] funct7,      // 指令的 funct7 欄位 (只需部分 bit 區分 ADD/SUB, SRL/SRA)
    output reg [4:0] ALUop     // ALU 操作碼 (可依實際需求擴增位數)
);

    // 定義 ALUop 常數 (依據自己的設計需求而定)
    localparam ALU_ADD  = 5'b00000;
    localparam ALU_SUB  = 5'b00001;
    localparam ALU_SLL  = 5'b00010;
    localparam ALU_SLT  = 5'b00011;
    localparam ALU_SLTU = 5'b00100;
    localparam ALU_XOR  = 5'b00101;
    localparam ALU_SRL  = 5'b00110;
    localparam ALU_SRA  = 5'b00111;
    localparam ALU_OR   = 5'b01000;
    localparam ALU_AND  = 5'b01001;
    // 如果要支援立即數或其他運算，可再擴增
      // B-type 指令
    localparam ALU_BEQ  = 5'b01010;
    localparam ALU_BNE  = 5'b01011;
    localparam ALU_BLT  = 5'b01100;
    localparam ALU_BGE  = 5'b01101;
    localparam ALU_BLTU = 5'b01110;
    localparam ALU_BGEU = 5'b01111;

    always @(*) begin
        case (opcode)
            7'b0110011: // R-type
                begin
                    case (funct3)
                    
    //ref : https://velog.io/@taegon1998/2.2-2-Basic-of-RISC-V
                        3'b000: // ADD / SUB
                            ALUop = (funct7[5] == 1'b1) ? ALU_SUB : ALU_ADD;
                        3'b001: ALUop = ALU_SLL; //SLL
                        3'b010: ALUop = ALU_SLT; //SLT
                        3'b011: ALUop = ALU_SLTU; //SLTU
                        3'b100: ALUop = ALU_XOR; //XOR
                        //---------------same funct3-------------------------
                        3'b101: // SRL / SRA
                            ALUop = (funct7[5] == 1'b1) ? ALU_SRA : ALU_SRL;
                        //---------------------------------------------------
                        3'b110: ALUop = ALU_OR;
                        3'b111: ALUop = ALU_AND;
                        default: ALUop = ALU_ADD;  // 預設給個安全值
                    endcase
                end
            7'b0010011: // I-type (ADDI, SLTI, XORI, ORI, ANDI, SLLI, SRLI, SRAI ...)
                begin
    //ref : https://www.chegg.com/homework-help/questions-and-answers/risc-v-instruction-show-value-opcode-op-source-register-rsl-destination-register-id-fields-q85052084
                    case (funct3)
                        3'b000: ALUop = ALU_ADD;   // ADDI
                        3'b010: ALUop = ALU_SLT;   // SLTI
                        3'b011: ALUop = ALU_SLTU;  // SLTIU
                        3'b100: ALUop = ALU_XOR;   // XORI
                        3'b110: ALUop = ALU_OR;    // ORI
                        3'b111: ALUop = ALU_AND;   // ANDI
                        3'b001: ALUop = ALU_SLL;   // SLLI
                        3'b101: // SRLI / SRAI
                            ALUop = (funct7[5] == 1'b1) ? ALU_SRA : ALU_SRL;
                        default: ALUop = ALU_ADD; 
                    endcase
                end
            7'b1100011: // B-type (Branch)
                case (funct3)
                    3'b000: ALUop = ALU_BEQ;
                    3'b001: ALUop = ALU_BNE;
                    3'b100: ALUop = ALU_BLT;
                    3'b101: ALUop = ALU_BGE;
                    3'b110: ALUop = ALU_BLTU;
                    3'b111: ALUop = ALU_BGEU;
                    default: ALUop = ALU_ADD;
                endcase
            default:
                ALUop = ALU_ADD; // 其他暫時預設成 ADD
        endcase
    end

endmodule

ALUctr_alu_imm_F/immgen.v
//------------------------- Immediate Generator (ImmGen) 模組 -------------------------
/*
 ┌─────────── 32-bit 指令格式 ───────────┐
 │  imm[11:0]  |  rs1  | funct3 |  rd  | opcode |
 │  31:20      | 19:15 | 14:12  | 11:7 | 6:0    |
 └──────────────────────────────────────┘
*/
module ImmGen (
    input  [31:0] instr,     // 指令
    output reg [31:0] imm_out // 立即數輸出
);

    always @(*) begin
        case (instr[6:0]) 
            7'b0010011: // I-type (ADDI, ORI, ANDI, SLTI, ...)
                imm_out = {{20{instr[31]}}, instr[31:20]}; // 符號擴展
            7'b1100011: // B-type (BEQ, BNE, BLT, BGE, BLTU, BGEU)
                imm_out = {{19{instr[31]}}, instr[31], instr[7], instr[30:25], instr[11:8], 1'b0}; // Branch offset
            default:
                imm_out = 32'b0;
        endcase
    end
endmodule

ALUctr_alu_imm_F/tb.v
`timescale 1ns / 100ps

module ALU_ALUctr_ImmGen_tb;
    reg [31:0] A;
    reg [31:0] instr; // 指令
    reg [6:0] opcode;
    reg [2:0] funct3;
    reg [6:0] funct7;
    wire [4:0] ALUop;
    wire [31:0] imm_out;
    wire [31:0] Y;
    wire zero;

    // 立即數生成器 (ImmGen) 實例化
    ImmGen imm_gen (
        .instr(instr),
        .imm_out(imm_out)
    );

    // ALU 控制單元 (ALUctr) 實例化
    ALUctr alu_ctrl (
        .opcode(opcode),
        .funct3(funct3),
        .funct7(funct7),
        .ALUop(ALUop)
    );

    // ALU 實例化
    ALU alu (
        .A(A),
        .B(imm_out), // 改用立即數
        .ALUop(ALUop),
        .Y(Y),
        .zero(zero)
    );

    // 測試程序
    initial begin
        $display("ALU + ALUctr + ImmGen: Testbench");
        $dumpfile("ALU_ALUctr_ImmGen_tb.vcd");  // VCD 波形輸出
        $dumpvars(0, ALU_ALUctr_ImmGen_tb);

        $display("------------------I-type 指令-------------------");
        opcode = 7'b0010011; // I-type 指令
        
        // 測試 ADDI (000 funct3) (A + imm)
        instr = 32'h00208213; // ADDI x4, x1, 2 (x4 = x1 + 2)
        $display("Instr: %b", instr);
        //you can just check the first 3 bits of the instruction to determine the constant you need to add to the register
        A = 32'h00000010;
        funct3 = 3'b000;
        #10;
        $display("ADDI: A=%h, imm=%h, Y=%h (Expect 12)", A, imm_out, Y);

        // 測試 SLTI (010 funct3) (有符號比較)
        instr = 32'h00308293; // SLTI x5, x1, 3 (x5 = (x1 < 3) ? 1 : 0)
        A = 32'hFFFFFFF0;
        funct3 = 3'b010;
        #10;
        $display("SLTI: A=%h, imm=%h, Y=%h (Expect 1)", A, imm_out, Y);

        // 測試 SLTIU (011 funct3) (無符號比較)
        instr = 32'h00309313; // SLTIU x6, x1, 3 (x6 = (x1 < 3) ? 1 : 0)
        A = 32'h00000010;
        funct3 = 3'b011;
        #10;
        $display("SLTIU: A=%h, imm=%h, Y=%h (Expect 0)", A, imm_out, Y);

        // 測試 XORI (100 funct3) (XOR)
        instr = 32'hF0F0F0F3; // XORI x7, x1, 0xF0F0F0F
        A = 32'h0000000F;
        funct3 = 3'b100;
        #10;
        $display("XORI: A=%h, imm=%h, Y=%h (Expect 0xF)", A, imm_out, Y);

        // 測試 ORI (110 funct3) (OR)
        instr = 32'hF0F0F0F3; // ORI x8, x1, 0xF0F0F0F
        A = 32'h0000F0F0;
        funct3 = 3'b110;
        #10;
        $display("ORI: A=%h, imm=%h, Y=%h (Expect 0x0F0F)", A, imm_out, Y);

        // 測試 ANDI (111 funct3) (AND)
        instr = 32'hF0F0F0F3; // ANDI x9, x1, 0xF0F0F0F
        A = 32'h0000F0F0;
        funct3 = 3'b111;
        #10;
        $display("ANDI: A=%h, imm=%h, Y=%h (Expect 00F000F0)", A, imm_out, Y);

        $display("------------------B-type 指令-------------------");
        opcode = 7'b1100011; // B-type 指令

        // 測試 BEQ (000 funct3) (A == B)
        instr = 32'h00050663; // BEQ x10, x0, offset
        A = 32'h00000010;
        funct3 = 3'b000;
        #10;
        $display("BEQ: A=%h, imm=%h, Y=%b (Expect 1)", A, imm_out, Y);

        // 測試 BNE (001 funct3) (A != B)
        instr = 32'h00051663; // BNE x10, x0, offset
        A = 32'h00000010;
        funct3 = 3'b001;
        #10;
        $display("BNE: A=%h, imm=%h, Y=%b (Expect 1)", A, imm_out, Y);

        // 測試 BLT (100 funct3) (A < B, 有號)
        instr = 32'h00054663; // BLT x10, x0, offset
        A = 32'hFFFFFFF0;
        funct3 = 3'b100;
        #10;
        $display("BLT: A=%h, imm=%h, Y=%b (Expect 1)", A, imm_out, Y);

        // 測試 BGE (101 funct3) (A >= B, 有號)
        instr = 32'h00055663; // BGE x10, x0, offset
        A = 32'h00000010;
        funct3 = 3'b101;
        #10;
        $display("BGE: A=%h, imm=%h, Y=%b (Expect 1)", A, imm_out, Y);

        // 測試 BLTU (110 funct3) (A < B, 無號)
        instr = 32'h00056663; // BLTU x10, x0, offset
        A = 32'h00000010;
        funct3 = 3'b110;
        #10;
        $display("BLTU: A=%h, imm=%h, Y=%b (Expect 1)", A, imm_out, Y);

        // 測試 BGEU (111 funct3) (A >= B, 無號)
        instr = 32'h00057663; // BGEU x10, x0, offset
        A = 32'hFFFFFFF0;
        funct3 = 3'b111;
        #10;
        $display("BGEU: A=%h, imm=%h, Y=%b (Expect 1)", A, imm_out, Y);

        $finish;
    end
endmodule

ALUctr_alu_imm_F/ALU_ALUctr_ImmGen_tb.vcd
$date
	Mon Mar 10 18:03:58 2025
$end
$version
	Icarus Verilog
$end
$timescale
	100ps
$end
$scope module ALU_ALUctr_ImmGen_tb $end
$var wire 1 ! zero $end
$var wire 32 " imm_out [31:0] $end
$var wire 32 # Y [31:0] $end
$var wire 5 $ ALUop [4:0] $end
$var reg 32 % A [31:0] $end
$var reg 3 & funct3 [2:0] $end
$var reg 7 ' funct7 [6:0] $end
$var reg 32 ( instr [31:0] $end
$var reg 7 ) opcode [6:0] $end
$scope module alu $end
$var wire 32 * A [31:0] $end
$var wire 1 ! zero $end
$var wire 32 + B [31:0] $end
$var wire 5 , ALUop [4:0] $end
$var reg 32 - Y [31:0] $end
$upscope $end
$scope module alu_ctrl $end
$var wire 3 . funct3 [2:0] $end
$var wire 7 / funct7 [6:0] $end
$var wire 7 0 opcode [6:0] $end
$var reg 5 1 ALUop [4:0] $end
$upscope $end
$scope module imm_gen $end
$var wire 32 2 instr [31:0] $end
$var reg 32 3 imm_out [31:0] $end
$upscope $end
$upscope $end
$enddefinitions $end
#0
$dumpvars
b10 3
b1000001000001000010011 2
b0 1
b10011 0
bx /
b0 .
b10010 -
b0 ,
b10 +
b10000 *
b10011 )
b1000001000001000010011 (
bx '
b0 &
b10000 %
b0 $
b10010 #
b10 "
0!
$end
#100
b11 $
b11 ,
b11 1
b1 #
b1 -
b11 "
b11 +
b11 3
b10 &
b10 .
b11111111111111111111111111110000 %
b11111111111111111111111111110000 *
b1100001000001010010011 (
b1100001000001010010011 2
#200
b100 $
b100 ,
b100 1
1!
b0 #
b0 -
b11 &
b11 .
b10000 %
b10000 *
b1100001001001100010011 (
b1100001001001100010011 2
#300
0!
b1111 #
b1111 -
b101 $
b101 ,
b101 1
b0 "
b0 +
b0 3
b100 &
b100 .
b1111 %
b1111 *
b11110000111100001111000011110011 (
b11110000111100001111000011110011 2
#400
b1000 $
b1000 ,
b1000 1
b1111000011110000 #
b1111000011110000 -
b110 &
b110 .
b1111000011110000 %
b1111000011110000 *
#500
1!
b0 #
b0 -
b1001 $
b1001 ,
b1001 1
b111 &
b111 .
#600
b1100 "
b1100 +
b1100 3
b1010 $
b1010 ,
b1010 1
b0 &
b0 .
b10000 %
b10000 *
b1010000011001100011 (
b1010000011001100011 2
b1100011 )
b1100011 0
#700
0!
b1 #
b1 -
b1011 $
b1011 ,
b1011 1
b1 &
b1 .
b1010001011001100011 (
b1010001011001100011 2
#800
b1100 $
b1100 ,
b1100 1
b100 &
b100 .
b11111111111111111111111111110000 %
b11111111111111111111111111110000 *
b1010100011001100011 (
b1010100011001100011 2
#900
b1101 $
b1101 ,
b1101 1
0!
b1 #
b1 -
b101 &
b101 .
b10000 %
b10000 *
b1010101011001100011 (
b1010101011001100011 2
#1000
1!
b0 #
b0 -
b1110 $
b1110 ,
b1110 1
b110 &
b110 .
b1010110011001100011 (
b1010110011001100011 2
#1100
0!
b1 #
b1 -
b1111 $
b1111 ,
b1111 1
b111 &
b111 .
b11111111111111111111111111110000 %
b11111111111111111111111111110000 *
b1010111011001100011 (
b1010111011001100011 2
