pc/pc.v
/*
 * Program Counter
 * 
 * The program counter is a register that holds the address of the next instruction
 */
module ProgramCounter (
    input wire clk, reset,
    input wire [31:0] next_pc,
    output reg [31:0] pc
);

always @(posedge clk or posedge reset) begin
    if (reset)
        pc <= 32'b0;
    else
        pc <= next_pc;
end

endmodule

pc/pctb.v
`timescale 1ns / 100ps

module pc_tb;

    reg clk, reset;
    reg [31:0] next_pc;
    wire [31:0] pc;

    // 例化 PC 模組
    ProgramCounter uut (
        .clk(clk),
        .reset(reset),
        .next_pc(next_pc),
        .pc(pc)
    );

    // 產生時脈訊號
    always #5 clk = ~clk;

    initial begin

        // 初始化
        clk = 0;
        reset = 1;
        next_pc = 32'h00000004;
        $dumpfile("testbench.vcd"); // 產生 VCD 檔案
        $dumpvars(0);    // 記錄所有訊號
        #10 reset = 0;  // 解除 reset，PC 應更新為 next_pc

        #10 next_pc = 32'h00000008;
        #10 next_pc = 32'h0000000C;
        #10 next_pc = 32'h00000010;

        #20 $finish;
    end

    initial begin
        $monitor("Time=%0t | Reset=%b | PC=%h | Next_PC=%h", $time, reset, pc, next_pc);
    end

endmodule

pc/testbench.vcd
$date
	Sun Mar  9 16:04:48 2025
$end
$version
	Icarus Verilog
$end
$timescale
	100ps
$end
$scope module pc_tb $end
$var wire 32 ! pc [31:0] $end
$var reg 1 " clk $end
$var reg 32 # next_pc [31:0] $end
$var reg 1 $ reset $end
$scope module uut $end
$var wire 1 " clk $end
$var wire 32 % next_pc [31:0] $end
$var wire 1 $ reset $end
$var reg 32 & pc [31:0] $end
$upscope $end
$upscope $end
$enddefinitions $end
#0
$dumpvars
b0 &
b100 %
1$
b100 #
0"
b0 !
$end
#50
1"
#100
0"
0$
#150
b100 !
b100 &
1"
#200
0"
b1000 #
b1000 %
#250
b1000 !
b1000 &
1"
#300
0"
b1100 #
b1100 %
#350
b1100 !
b1100 &
1"
#400
0"
b10000 #
b10000 %
#450
b10000 !
b10000 &
1"
