alu/alu.v

//----------------------------- ALU 模組 -----------------------------
module ALU (
    input  [31:0] A,       // 來源操作數1
    input  [31:0] B,       // 來源操作數2
    input  [4:0]  ALUop,   // 由 ALUctr 輸入的操作碼
    output reg [31:0] Y,   // 計算結果
    output zero            // 結果是否為 0
);

    wire [31:0] sub_temp;
    assign sub_temp = A - B;

    always @(*) begin
        case (ALUop)
            5'b00000: Y = A + B;                  // ALU_ADD
            5'b00001: Y = A - B;                  // ALU_SUB
            5'b00010: Y = A << B[4:0];            // ALU_SLL
            5'b00011: Y = ($signed(A) < $signed(B)) ? 32'b1 : 32'b0;  // ALU_SLT (有號比較)
            5'b00100: Y = (A < B) ? 32'b1 : 32'b0; // ALU_SLTU (無號比較)
            5'b00101: Y = A ^ B;                  // ALU_XOR
            5'b00110: Y = A >> B[4:0];            // ALU_SRL (邏輯右移)
            5'b00111: Y = $signed(A) >>> B[4:0];  // ALU_SRA (算術右移)
            5'b01000: Y = A | B;                  // ALU_OR
            5'b01001: Y = A & B;                  // ALU_AND
            default:  Y = 32'b0;
        endcase
    end

    // zero flag：當計算結果為0時拉高
    assign zero = (Y == 32'b0) ? 1'b1 : 1'b0;

endmodule

alu/alu_tb.v
`timescale 1ns / 1ps

module ALU_tb;
    reg [31:0] A, B;
    reg [4:0] ALUop;
    wire [31:0] Y;
    wire zero;

    // ALU 實例化
    ALU uut (
        .A(A),
        .B(B),
        .ALUop(ALUop),
        .Y(Y),
        .zero(zero)
    );

    // 測試程序
    initial begin
        $dumpfile("ALU_tb.vcd");  // VCD 波形輸出
        $dumpvars(0, ALU_tb);

        // 測試 ADD (00000)
        A = 32'h00000010; B = 32'h00000020; ALUop = 5'b00000;
        #10;
        $display("ADD: A=%h, B=%h, Y=%h (Expect 30)", A, B, Y);

        // 測試 SUB (00001)
        A = 32'h00000030; B = 32'h00000010; ALUop = 5'b00001;
        #10;
        $display("SUB: A=%h, B=%h, Y=%h (Expect 20)", A, B, Y);

        // 測試 SLL (00010)
        A = 32'h00000001; B = 32'h00000002; ALUop = 5'b00010;
        #10;
        $display("SLL: A=%h, B=%h, Y=%h (Expect 4)", A, B, Y);

        // 測試 SLT (00011) (有號比較)
        A = 32'hFFFFFFF0; B = 32'h00000010; ALUop = 5'b00011;
        #10;
        $display("SLT: A=%h, B=%h, Y=%h (Expect 1)", A, B, Y);

        // 測試 SLTU (00100) (無號比較)
        A = 32'h00000010; B = 32'hFFFFFFF0; ALUop = 5'b00100;
        #10;
        $display("SLTU: A=%h, B=%h, Y=%h (Expect 1)", A, B, Y);

        // 測試 XOR (00101)
        A = 32'h0000000F; B = 32'h000000F0; ALUop = 5'b00101;
        #10;
        $display("XOR: A=%h, B=%h, Y=%h (Expect 0xFF)", A, B, Y);

        // 測試 SRL (00110)
        A = 32'h00000010; B = 32'h00000002; ALUop = 5'b00110;
        #10;
        $display("SRL: A=%h, B=%h, Y=%h (Expect 4)", A, B, Y);

        // 測試 SRA (00111)
        A = 32'h80000000; B = 32'h00000002; ALUop = 5'b00111;
        #10;
        $display("SRA: A=%h, B=%h, Y=%h (Expect E0000000)", A, B, Y);

        // 測試 OR (01000)
        A = 32'h0000F0F0; B = 32'h00F000F0; ALUop = 5'b01000;
        #10;
        $display("OR: A=%h, B=%h, Y=%h (Expect 00F0F0F0)", A, B, Y);

        // 測試 AND (01001)
        A = 32'h0000F0F0; B = 32'h00F000F0; ALUop = 5'b01001;
        #10;
        $display("AND: A=%h, B=%h, Y=%h (Expect 000000F0)", A, B, Y);

        // 測試 zero flag
        A = 32'h00000010; B = 32'h00000010; ALUop = 5'b00001;
        #10;
        $display("Zero Flag: A=%h, B=%h, Y=%h, Zero=%b (Expect Zero=1)", A, B, Y, zero);

        $finish;
    end
endmodule

alu/ALU_tb.vcd
$date
	Mon Mar 10 15:33:51 2025
$end
$version
	Icarus Verilog
$end
$timescale
	1ps
$end
$scope module ALU_tb $end
$var wire 1 ! zero $end
$var wire 32 " Y [31:0] $end
$var reg 32 # A [31:0] $end
$var reg 5 $ ALUop [4:0] $end
$var reg 32 % B [31:0] $end
$scope module uut $end
$var wire 32 & A [31:0] $end
$var wire 5 ' ALUop [4:0] $end
$var wire 32 ( B [31:0] $end
$var wire 1 ! zero $end
$var wire 32 ) sub_temp [31:0] $end
$var reg 32 * Y [31:0] $end
$upscope $end
$upscope $end
$enddefinitions $end
#0
$dumpvars
b110000 *
b11111111111111111111111111110000 )
b100000 (
b0 '
b10000 &
b100000 %
b0 $
b10000 #
b110000 "
0!
$end
#10000
b100000 "
b100000 *
b1 $
b1 '
b10000 %
b10000 (
b100000 )
b110000 #
b110000 &
#20000
b100 "
b100 *
b10 $
b10 '
b10 %
b10 (
b11111111111111111111111111111111 )
b1 #
b1 &
#30000
b1 "
b1 *
b11 $
b11 '
b10000 %
b10000 (
b11111111111111111111111111100000 )
b11111111111111111111111111110000 #
b11111111111111111111111111110000 &
#40000
b100 $
b100 '
b11111111111111111111111111110000 %
b11111111111111111111111111110000 (
b100000 )
b10000 #
b10000 &
#50000
b11111111 "
b11111111 *
b101 $
b101 '
b11110000 %
b11110000 (
b11111111111111111111111100011111 )
b1111 #
b1111 &
#60000
b100 "
b100 *
b110 $
b110 '
b10 %
b10 (
b1110 )
b10000 #
b10000 &
#70000
b11100000000000000000000000000000 "
b11100000000000000000000000000000 *
b111 $
b111 '
b1111111111111111111111111111110 )
b10000000000000000000000000000000 #
b10000000000000000000000000000000 &
#80000
b111100001111000011110000 "
b111100001111000011110000 *
b1000 $
b1000 '
b111100000000000011110000 %
b111100000000000011110000 (
b11111111000100001111000000000000 )
b1111000011110000 #
b1111000011110000 &
#90000
b11110000 "
b11110000 *
b1001 $
b1001 '
#100000
1!
b0 "
b0 *
b1 $
b1 '
b10000 %
b10000 (
b0 )
b10000 #
b10000 &
